xlcrf/CRF.py
xlcrf/__init__.py
xlcrf/argparser.py
xlcrf/scripts.py
xlcrf-0.0.7.dist-info/METADATA
xlcrf-0.0.7.dist-info/WHEEL
xlcrf-0.0.7.dist-info/entry_points.txt
xlcrf-0.0.7.dist-info/top_level.txt
xlcrf-0.0.7.dist-info/RECORD
