Metadata-Version: 2.1
Name: xlcrf
Version: 0.0.7
Summary: Small tools to create Excel CRFs from structure files
Home-page: https://github.com/lbraglia/xlcrf
Author: Luca Braglia
Author-email: lbraglia@gmail.com
Project-URL: Bug Tracker, https://github.com/lbraglia/xlcrf/issues
Classifier: Programming Language :: Python :: 3
Classifier: License :: OSI Approved :: MIT License
Classifier: Operating System :: OS Independent
Requires-Python: >=3.6
Requires-Dist: numpy
Requires-Dist: pandas
Requires-Dist: xlsxwriter
